slumba/__init__.py
slumba/aggregate.py
slumba/exceptions.py
slumba/numbaext.py
slumba/scalar.py
slumba/sqlite.py
slumba-3.1.0.dist-info/LICENSE
slumba-3.1.0.dist-info/WHEEL
slumba-3.1.0.dist-info/METADATA
slumba-3.1.0.dist-info/RECORD
