Metadata-Version: 2.1
Name: slumba
Version: 3.1.0
Summary: JITted SQLite user-defined functions and aggregates
Home-page: https://github.com/cpcloud/slumba
Author: Phillip Cloud
Author-email: 417981+cpcloud@users.noreply.github.com
Maintainer: Phillip Cloud
Maintainer-email: 417981+cpcloud@users.noreply.github.com
Requires-Python: >=3.7.8,<3.10
Classifier: Development Status :: 2 - Pre-Alpha
Classifier: Intended Audience :: Developers
Classifier: Natural Language :: English
Classifier: Programming Language :: Python :: 3
Classifier: Programming Language :: Python :: 3.7
Classifier: Programming Language :: Python :: 3.8
Classifier: Programming Language :: Python :: 3.9
Requires-Dist: llvmlite (==0.36.0)
Requires-Dist: numba (==0.53.1)
Project-URL: Repository, https://github.com/cpcloud/slumba
